expiringdictx-1.1.0.dist-info/METADATA
expiringdictx-1.1.0.dist-info/WHEEL
expiringdictx-1.1.0.dist-info/licenses/LICENSE
expiringdictx/__init__.py
expiringdictx/expire.py
expiringdictx/simple.py
expiringdictx-1.1.0.dist-info/RECORD
