Metadata-Version: 2.1
Name: expiringdictx
Version: 1.1.0
Summary: 提供一个带有过期时间的字典数据结构，适用于缓存和临时存储。
Keywords: expire,dict,lru
Home-page: https://github.com/AzideCupric/expiringdictx
Author-Email: AzideCupric <rukuy@qq.com>
License: MIT
Classifier: Development Status :: 4 - Beta
Classifier: Operating System :: POSIX :: Linux
Classifier: Operating System :: Microsoft :: Windows
Classifier: Operating System :: MacOS
Classifier: Programming Language :: Python :: 3.10
Classifier: Programming Language :: Python :: 3.11
Classifier: Programming Language :: Python :: 3.12
Classifier: Programming Language :: Python :: Implementation :: CPython
Classifier: License :: OSI Approved :: MIT License
Project-URL: Homepage, https://github.com/AzideCupric/expiringdictx
Project-URL: Repository, https://github.com/AzideCupric/expiringdictx
Project-URL: Documentation, https://github.com/AzideCupric/expiringdictx
Requires-Python: <4,>=3.9
Requires-Dist: lru-dict<2.0.0,>=1.3.0
